gpt_api/__init__.py
gpt_api/__main__.py
gpt_api/api.py
gpt_api/cli.py
gpt_api_python-1.0.3.dist-info/LICENSE
gpt_api_python-1.0.3.dist-info/METADATA
gpt_api_python-1.0.3.dist-info/WHEEL
gpt_api_python-1.0.3.dist-info/entry_points.txt
gpt_api_python-1.0.3.dist-info/top_level.txt
gpt_api_python-1.0.3.dist-info/RECORD
