Metadata-Version: 2.1
Name: gpt-api-python
Version: 1.0.3
Summary: Python client sdk to access GPT's AI-powered conversational functionality (without OpenAI API key nor VPN)
Author-email: Beeno Tung <aabbcc1241@yahoo.com.hk>
License: BSD 2-Clause License
Project-URL: Homepage, https://github.com/beenotung/gpt-api
Keywords: gpt,gpt-api,openai,language-model,nlp,ai,chatbot,text-generation,text-summarization,translation,question-answering,sentiment-analysis,content-moderation,conversational-ai,poe,sdk
Classifier: License :: OSI Approved :: BSD License
Classifier: Programming Language :: Python
Classifier: Programming Language :: Python :: 3
License-File: LICENSE
Requires-Dist: requests
